main.py
super_rag-0.0.10.dist-info/METADATA
super_rag-0.0.10.dist-info/WHEEL
super_rag-0.0.10.dist-info/RECORD
