Metadata-Version: 2.1
Name: super-rag
Version: 0.0.10
Summary: Super-performant RAG pipelines for AI apps
Author: Superagent Technologies Inc.
Requires-Python: >=3.9,<3.12
Classifier: Programming Language :: Python :: 3
Classifier: Programming Language :: Python :: 3.9
Classifier: Programming Language :: Python :: 3.10
Classifier: Programming Language :: Python :: 3.11
Requires-Dist: astrapy (>=0.7.4,<0.8.0)
Requires-Dist: black (>=23.12.1,<24.0.0)
Requires-Dist: cmake (>=3.28.1,<4.0.0)
Requires-Dist: cohere (>=4.46,<5.0)
Requires-Dist: docx2txt (>=0.8,<0.9)
Requires-Dist: e2b (>=0.14.7,<0.15.0)
Requires-Dist: fastapi (>=0.109.2,<0.110.0)
Requires-Dist: flake8 (>=7.0.0,<8.0.0)
Requires-Dist: gunicorn (>=21.2.0,<22.0.0)
Requires-Dist: llama-index (>=0.9.46,<0.10.0)
Requires-Dist: openai (>=1.12.0,<2.0.0)
Requires-Dist: pinecone-client (>=3.0.2,<4.0.0)
Requires-Dist: pypdf (>=4.0.1,<5.0.0)
Requires-Dist: python-decouple (>=3.8,<4.0)
Requires-Dist: python-dotenv (>=1.0.1,<2.0.0)
Requires-Dist: qdrant-client (>=1.7.3,<2.0.0)
Requires-Dist: ruff (>=0.2.1,<0.3.0)
Requires-Dist: semantic-router (>=0.0.26,<0.0.27)
Requires-Dist: tiktoken (>=0.6.0,<0.7.0)
Requires-Dist: tqdm (>=4.66.2,<5.0.0)
Requires-Dist: unstructured-client (>=0.18.0,<0.19.0)
Requires-Dist: unstructured[google-drive] (>=0.12.4,<0.13.0)
Requires-Dist: uvicorn (>=0.27.1,<0.28.0)
Requires-Dist: vulture (>=2.11,<3.0)
Requires-Dist: weaviate-client (>=4.1.2,<5.0.0)
